examples/python_entrypoint_stub.py
examples/js/cli/package.json
examples/js/cli/pnpm-lock.yaml
examples/js/cli/tsconfig.json
examples/js/cli/src/cli.ts
examples/js/langgraph-js-example/package.json
examples/js/langgraph-js-example/pnpm-lock.yaml
examples/js/langgraph-js-example/tsconfig.json
examples/js/langgraph-js-example/src/agent.ts
examples/js/langgraph-js-example/src/agentExecutor.ts
examples/js/langgraph-js-example/src/index.ts
examples/js/vercel-ai-example/package.json
examples/js/vercel-ai-example/pnpm-lock.yaml
examples/js/vercel-ai-example/tsconfig.json
examples/js/vercel-ai-example/src/agent.ts
examples/js/vercel-ai-example/src/agentExecutor.ts
examples/js/vercel-ai-example/src/baseAgentExecutor.ts
examples/js/vercel-ai-example/src/index.ts
examples/mcp/tshirt_store_langgraph_mcp/README.md
examples/mcp/tshirt_store_langgraph_mcp/__init__.py
examples/mcp/tshirt_store_langgraph_mcp/__main__.py
examples/mcp/tshirt_store_langgraph_mcp/mcp_agent_wrapper.py
examples/mcp/tshirt_store_langgraph_mcp/shirtify_agent.py
examples/tshirt_store_agent/__init__.py
examples/tshirt_store_agent/__main__.py
examples/tshirt_store_agent/test_client.py
examples/tshirt_store_agent/tshirt_store_agent.py
examples/tshirt_store_agent/tshirt_store_agent_executor.py
examples/tshirt_store_langgraph_agent/__init__.py
examples/tshirt_store_langgraph_agent/__main__.py
examples/tshirt_store_langgraph_agent/python_entrypoint_shirtify.py
examples/tshirt_store_langgraph_agent/shirtify_langgraph_agent.py
examples/tshirt_store_langgraph_agent/shirtify_langgraph_agent_executor.py
rogue/__init__.py
rogue/__main__.py
rogue/github_action_docs.md
rogue/run_cli.py
rogue/run_server.py
rogue/run_tui.py
rogue/common/__init__.py
rogue/common/agent_model_wrapper.py
rogue/common/agent_sessions.py
rogue/common/generic_agent_executor.py
rogue/common/generic_task_callback.py
rogue/common/remote_agent_connection.py
rogue/common/tui_installer.py
rogue/common/update_checker.py
rogue/common/version.py
rogue_ai-0.3.4.dist-info/METADATA
rogue_ai-0.3.4.dist-info/WHEEL
rogue_ai-0.3.4.dist-info/entry_points.txt
rogue_ai-0.3.4.dist-info/licenses/LICENSE.md
rogue_ai-0.3.4.dist-info/RECORD
