Metadata-Version: 2.4
Name: rogue-ai
Version: 0.3.4
Summary: Rogue agent evaluator by Qualifire
License-File: LICENSE.md
Requires-Python: >=3.10
Requires-Dist: a2a-sdk==0.2.10
Requires-Dist: backoff>=2.2.1
Requires-Dist: boto3>=1.40.69
Requires-Dist: click>=8.0.0
Requires-Dist: datasets==3.6.0
Requires-Dist: fastapi>=0.121.0
Requires-Dist: fastmcp>=2.12.5
Requires-Dist: google-adk==1.5.0
Requires-Dist: langchain-openai>=0.3.35
Requires-Dist: litellm==1.76.1
Requires-Dist: loguru==0.7.3
Requires-Dist: platformdirs>=4.3.8
Requires-Dist: psutil>=7.0.0
Requires-Dist: pydantic-yaml==1.5.1
Requires-Dist: pydantic==2.11.7
Requires-Dist: python-dotenv==1.1.1
Requires-Dist: requests>=2.32.4
Requires-Dist: rich>=14.0.0
Requires-Dist: rogue-ai-sdk>=0.1.3
Requires-Dist: uvicorn>=0.38.0
